dino_chrome/__init__.py
dino_chrome/main.py
Dino_Chrome-0.1.dist-info/LICENSE
Dino_Chrome-0.1.dist-info/METADATA
Dino_Chrome-0.1.dist-info/WHEEL
Dino_Chrome-0.1.dist-info/top_level.txt
Dino_Chrome-0.1.dist-info/RECORD
